[{"substring":"Sai","answers":["MF","SH","KN","LC","VC"],"question":"Name starts with 'Sai'"},{"substring":"Mal","answers":["ML","MT","MW","MV","MY"],"question":"Name starts with 'Mal'"},{"substring":"Bel","answers":["BE","BY","BZ"],"question":"Name starts with 'Bel'"},{"substring":"Gre","answers":["GR","GD","GL"],"question":"Name starts with 'Gre'"},{"substring":"Uni","answers":["GB","US","AE"],"question":"Name starts with 'Uni'"},{"substring":"Sou","answers":["ZA","SS","KR"],"question":"Name starts with 'Sou'"},{"substring":"Mon","answers":["ME","MC","MN"],"question":"Name starts with 'Mon'"},{"substring":"Nor","answers":["NO","NF","KP"],"question":"Name starts with 'Nor'"},{"substring":"Bur","answers":["BF","BI"],"question":"Name starts with 'Bur'"},{"substring":"Bah","answers":["BH","BS"],"question":"Name starts with 'Bah'"},{"substring":"Tur","answers":["TM","TR"],"question":"Name starts with 'Tur'"},{"substring":"Gui","answers":["GW","GN"],"question":"Name starts with 'Gui'"},{"substring":"Hon","answers":["HK","HN"],"question":"Name starts with 'Hon'"},{"substring":"Pal","answers":["PS","PW"],"question":"Name starts with 'Pal'"},{"substring":"Ira","answers":["IQ","IR"],"question":"Name starts with 'Ira'"},{"substring":"Mac","answers":["MO","MK"],"question":"Name starts with 'Mac'"},{"substring":"Mau","answers":["MU","MR"],"question":"Name starts with 'Mau'"},{"substring":"Nig","answers":["NE","NG"],"question":"Name starts with 'Nig'"},{"substring":"Chi","answers":["CN","CL"],"question":"Name starts with 'Chi'"},{"substring":"Cam","answers":["CM","KH"],"question":"Name starts with 'Cam'"},{"substring":"Slo","answers":["SK","SI"],"question":"Name starts with 'Slo'"},{"substring":"Dom","answers":["DO","DM"],"question":"Name starts with 'Dom'"},{"substring":"Lib","answers":["LR","LY"],"question":"Name starts with 'Lib'"},{"substring":"Ant","answers":["AG","AQ"],"question":"Name starts with 'Ant'"},{"substring":"Aus","answers":["AU","AT"],"question":"Name starts with 'Aus'"},{"substring":"Ind","answers":["IN","ID"],"question":"Name starts with 'Ind'"},{"substring":"Ban","answers":["BD"],"question":"Name starts with 'Ban'"},{"substring":"Bul","answers":["BG"],"question":"Name starts with 'Bul'"},{"substring":"Bos","answers":["BA"],"question":"Name starts with 'Bos'"},{"substring":"Bar","answers":["BB"],"question":"Name starts with 'Bar'"},{"substring":"Ber","answers":["BM"],"question":"Name starts with 'Ber'"},{"substring":"Bru","answers":["BN"],"question":"Name starts with 'Bru'"},{"substring":"Bol","answers":["BO"],"question":"Name starts with 'Bol'"},{"substring":"Ben","answers":["BJ"],"question":"Name starts with 'Ben'"},{"substring":"Bhu","answers":["BT"],"question":"Name starts with 'Bhu'"},{"substring":"Jam","answers":["JM"],"question":"Name starts with 'Jam'"},{"substring":"Bou","answers":["BV"],"question":"Name starts with 'Bou'"},{"substring":"Bot","answers":["BW"],"question":"Name starts with 'Bot'"},{"substring":"Sam","answers":["WS"],"question":"Name starts with 'Sam'"},{"substring":"Bra","answers":["BR"],"question":"Name starts with 'Bra'"},{"substring":"Jer","answers":["JE"],"question":"Name starts with 'Jer'"},{"substring":"Rus","answers":["RU"],"question":"Name starts with 'Rus'"},{"substring":"Rwa","answers":["RW"],"question":"Name starts with 'Rwa'"},{"substring":"Ser","answers":["RS"],"question":"Name starts with 'Ser'"},{"substring":"Eas","answers":["TL"],"question":"Name starts with 'Eas'"},{"substring":"Reu","answers":["RE"],"question":"Name starts with 'Reu'"},{"substring":"Taj","answers":["TJ"],"question":"Name starts with 'Taj'"},{"substring":"Rom","answers":["RO"],"question":"Name starts with 'Rom'"},{"substring":"Gua","answers":["GT"],"question":"Name starts with 'Gua'"},{"substring":"Equ","answers":["GQ"],"question":"Name starts with 'Equ'"},{"substring":"Jap","answers":["JP"],"question":"Name starts with 'Jap'"},{"substring":"Guy","answers":["GY"],"question":"Name starts with 'Guy'"},{"substring":"Gue","answers":["GG"],"question":"Name starts with 'Gue'"},{"substring":"Geo","answers":["GE"],"question":"Name starts with 'Geo'"},{"substring":"Gab","answers":["GA"],"question":"Name starts with 'Gab'"},{"substring":"Gam","answers":["GM"],"question":"Name starts with 'Gam'"},{"substring":"Gha","answers":["GH"],"question":"Name starts with 'Gha'"},{"substring":"Oma","answers":["OM"],"question":"Name starts with 'Oma'"},{"substring":"Tun","answers":["TN"],"question":"Name starts with 'Tun'"},{"substring":"Jor","answers":["JO"],"question":"Name starts with 'Jor'"},{"substring":"Cro","answers":["HR"],"question":"Name starts with 'Cro'"},{"substring":"Hai","answers":["HT"],"question":"Name starts with 'Hai'"},{"substring":"Hun","answers":["HU"],"question":"Name starts with 'Hun'"},{"substring":"Ven","answers":["VE"],"question":"Name starts with 'Ven'"},{"substring":"Pue","answers":["PR"],"question":"Name starts with 'Pue'"},{"substring":"Por","answers":["PT"],"question":"Name starts with 'Por'"},{"substring":"Sva","answers":["SJ"],"question":"Name starts with 'Sva'"},{"substring":"Par","answers":["PY"],"question":"Name starts with 'Par'"},{"substring":"Pan","answers":["PA"],"question":"Name starts with 'Pan'"},{"substring":"Pap","answers":["PG"],"question":"Name starts with 'Pap'"},{"substring":"Per","answers":["PE"],"question":"Name starts with 'Per'"},{"substring":"Pak","answers":["PK"],"question":"Name starts with 'Pak'"},{"substring":"Phi","answers":["PH"],"question":"Name starts with 'Phi'"},{"substring":"Pol","answers":["PL"],"question":"Name starts with 'Pol'"},{"substring":"Zam","answers":["ZM"],"question":"Name starts with 'Zam'"},{"substring":"Wes","answers":["EH"],"question":"Name starts with 'Wes'"},{"substring":"Est","answers":["EE"],"question":"Name starts with 'Est'"},{"substring":"Egy","answers":["EG"],"question":"Name starts with 'Egy'"},{"substring":"Ecu","answers":["EC"],"question":"Name starts with 'Ecu'"},{"substring":"Ita","answers":["IT"],"question":"Name starts with 'Ita'"},{"substring":"Vie","answers":["VN"],"question":"Name starts with 'Vie'"},{"substring":"Sol","answers":["SB"],"question":"Name starts with 'Sol'"},{"substring":"Eth","answers":["ET"],"question":"Name starts with 'Eth'"},{"substring":"Som","answers":["SO"],"question":"Name starts with 'Som'"},{"substring":"Zim","answers":["ZW"],"question":"Name starts with 'Zim'"},{"substring":"Sau","answers":["SA"],"question":"Name starts with 'Sau'"},{"substring":"Spa","answers":["ES"],"question":"Name starts with 'Spa'"},{"substring":"Eri","answers":["ER"],"question":"Name starts with 'Eri'"},{"substring":"Mol","answers":["MD"],"question":"Name starts with 'Mol'"},{"substring":"Mad","answers":["MG"],"question":"Name starts with 'Mad'"},{"substring":"Mor","answers":["MA"],"question":"Name starts with 'Mor'"},{"substring":"Uzb","answers":["UZ"],"question":"Name starts with 'Uzb'"},{"substring":"Mya","answers":["MM"],"question":"Name starts with 'Mya'"},{"substring":"Mar","answers":["MH"],"question":"Name starts with 'Mar'"},{"substring":"Isl","answers":["IM"],"question":"Name starts with 'Isl'"},{"substring":"Uga","answers":["UG"],"question":"Name starts with 'Uga'"},{"substring":"Tan","answers":["TZ"],"question":"Name starts with 'Tan'"},{"substring":"Mex","answers":["MX"],"question":"Name starts with 'Mex'"},{"substring":"Isr","answers":["IL"],"question":"Name starts with 'Isr'"},{"substring":"Fra","answers":["FR"],"question":"Name starts with 'Fra'"},{"substring":"Fin","answers":["FI"],"question":"Name starts with 'Fin'"},{"substring":"Fij","answers":["FJ"],"question":"Name starts with 'Fij'"},{"substring":"Fal","answers":["FK"],"question":"Name starts with 'Fal'"},{"substring":"Mic","answers":["FM"],"question":"Name starts with 'Mic'"},{"substring":"Far","answers":["FO"],"question":"Name starts with 'Far'"},{"substring":"Nic","answers":["NI"],"question":"Name starts with 'Nic'"},{"substring":"Net","answers":["NL"],"question":"Name starts with 'Net'"},{"substring":"Nam","answers":["NA"],"question":"Name starts with 'Nam'"},{"substring":"Van","answers":["VU"],"question":"Name starts with 'Van'"},{"substring":"New","answers":["NZ"],"question":"Name starts with 'New'"},{"substring":"Nep","answers":["NP"],"question":"Name starts with 'Nep'"},{"substring":"Nau","answers":["NR"],"question":"Name starts with 'Nau'"},{"substring":"Kos","answers":["XK"],"question":"Name starts with 'Kos'"},{"substring":"Ivo","answers":["CI"],"question":"Name starts with 'Ivo'"},{"substring":"Swi","answers":["CH"],"question":"Name starts with 'Swi'"},{"substring":"Col","answers":["CO"],"question":"Name starts with 'Col'"},{"substring":"Can","answers":["CA"],"question":"Name starts with 'Can'"},{"substring":"Rep","answers":["CG"],"question":"Name starts with 'Rep'"},{"substring":"Cen","answers":["CF"],"question":"Name starts with 'Cen'"},{"substring":"Dem","answers":["CD"],"question":"Name starts with 'Dem'"},{"substring":"Cze","answers":["CZ"],"question":"Name starts with 'Cze'"},{"substring":"Cyp","answers":["CY"],"question":"Name starts with 'Cyp'"},{"substring":"Cos","answers":["CR"],"question":"Name starts with 'Cos'"},{"substring":"Cap","answers":["CV"],"question":"Name starts with 'Cap'"},{"substring":"Cub","answers":["CU"],"question":"Name starts with 'Cub'"},{"substring":"Esw","answers":["SZ"],"question":"Name starts with 'Esw'"},{"substring":"Syr","answers":["SY"],"question":"Name starts with 'Syr'"},{"substring":"Kyr","answers":["KG"],"question":"Name starts with 'Kyr'"},{"substring":"Ken","answers":["KE"],"question":"Name starts with 'Ken'"},{"substring":"Sur","answers":["SR"],"question":"Name starts with 'Sur'"},{"substring":"Kir","answers":["KI"],"question":"Name starts with 'Kir'"},{"substring":"Com","answers":["KM"],"question":"Name starts with 'Com'"},{"substring":"Sao","answers":["ST"],"question":"Name starts with 'Sao'"},{"substring":"Kuw","answers":["KW"],"question":"Name starts with 'Kuw'"},{"substring":"Sen","answers":["SN"],"question":"Name starts with 'Sen'"},{"substring":"San","answers":["SM"],"question":"Name starts with 'San'"},{"substring":"Sie","answers":["SL"],"question":"Name starts with 'Sie'"},{"substring":"Sey","answers":["SC"],"question":"Name starts with 'Sey'"},{"substring":"Kaz","answers":["KZ"],"question":"Name starts with 'Kaz'"},{"substring":"Sin","answers":["SG"],"question":"Name starts with 'Sin'"},{"substring":"Swe","answers":["SE"],"question":"Name starts with 'Swe'"},{"substring":"Sud","answers":["SD"],"question":"Name starts with 'Sud'"},{"substring":"Dji","answers":["DJ"],"question":"Name starts with 'Dji'"},{"substring":"Den","answers":["DK"],"question":"Name starts with 'Den'"},{"substring":"Ger","answers":["DE"],"question":"Name starts with 'Ger'"},{"substring":"Yem","answers":["YE"],"question":"Name starts with 'Yem'"},{"substring":"Alg","answers":["DZ"],"question":"Name starts with 'Alg'"},{"substring":"Uru","answers":["UY"],"question":"Name starts with 'Uru'"},{"substring":"Leb","answers":["LB"],"question":"Name starts with 'Leb'"},{"substring":"Lao","answers":["LA"],"question":"Name starts with 'Lao'"},{"substring":"Tuv","answers":["TV"],"question":"Name starts with 'Tuv'"},{"substring":"Tai","answers":["TW"],"question":"Name starts with 'Tai'"},{"substring":"Tri","answers":["TT"],"question":"Name starts with 'Tri'"},{"substring":"Sri","answers":["LK"],"question":"Name starts with 'Sri'"},{"substring":"Lie","answers":["LI"],"question":"Name starts with 'Lie'"},{"substring":"Lat","answers":["LV"],"question":"Name starts with 'Lat'"},{"substring":"Ton","answers":["TO"],"question":"Name starts with 'Ton'"},{"substring":"Lit","answers":["LT"],"question":"Name starts with 'Lit'"},{"substring":"Lux","answers":["LU"],"question":"Name starts with 'Lux'"},{"substring":"Les","answers":["LS"],"question":"Name starts with 'Les'"},{"substring":"Tha","answers":["TH"],"question":"Name starts with 'Tha'"},{"substring":"Tog","answers":["TG"],"question":"Name starts with 'Tog'"},{"substring":"Cha","answers":["TD"],"question":"Name starts with 'Cha'"},{"substring":"Vat","answers":["VA"],"question":"Name starts with 'Vat'"},{"substring":"And","answers":["AD"],"question":"Name starts with 'And'"},{"substring":"Afg","answers":["AF"],"question":"Name starts with 'Afg'"},{"substring":"Ice","answers":["IS"],"question":"Name starts with 'Ice'"},{"substring":"Arm","answers":["AM"],"question":"Name starts with 'Arm'"},{"substring":"Alb","answers":["AL"],"question":"Name starts with 'Alb'"},{"substring":"Ang","answers":["AO"],"question":"Name starts with 'Ang'"},{"substring":"Arg","answers":["AR"],"question":"Name starts with 'Arg'"},{"substring":"Aru","answers":["AW"],"question":"Name starts with 'Aru'"},{"substring":"Ala","answers":["AX"],"question":"Name starts with 'Ala'"},{"substring":"Aze","answers":["AZ"],"question":"Name starts with 'Aze'"},{"substring":"Ire","answers":["IE"],"question":"Name starts with 'Ire'"},{"substring":"Ukr","answers":["UA"],"question":"Name starts with 'Ukr'"},{"substring":"Qat","answers":["QA"],"question":"Name starts with 'Qat'"},{"substring":"Moz","answers":["MZ"],"question":"Name starts with 'Moz'"}]